{
  "matches": [
    {
      "league": "UEFA Champions League",
      "home": "Bayer Leverkusen",
      "home_logo": "https://i1.wp.com/api.sofascore1.com/api/v1/team/2681/image",
      "away": "Arsenal",
      "away_logo": "https://i1.wp.com/api.sofascore1.com/api/v1/team/42/image",
      "kickoff": "2026-03-11T16:45:00Z",
      "duration": 2
    },
    {
      "league": "UEFA Champions League",
      "home": "Real Madrid",
      "home_logo": "https://i1.wp.com/api.sofascore1.com/api/v1/team/2829/image",
      "away": "Manchester City",
      "away_logo": "https://i1.wp.com/api.sofascore1.com/api/v1/team/17/image",
      "kickoff": "2026-03-11T20:00:00Z",
      "duration": 2
    },
    {
      "league": "UEFA Champions League",
      "home": "PSG",
      "home_logo": "https://i1.wp.com/api.sofascore1.com/api/v1/team/1644/image",
      "away": "Chelsea",
      "away_logo": "https://i1.wp.com/api.sofascore1.com/api/v1/team/38/image",
      "kickoff": "2026-03-11T20:00:00Z",
      "duration": 2
    },
    {
      "league": "English Championship",
      "home": "Coventry City",
      "home_logo": "https://i1.wp.com/api.sofascore1.com/api/v1/team/1049/image",
      "away": "Preston North End",
      "away_logo": "https://i1.wp.com/api.sofascore1.com/api/v1/team/1785/image",
      "kickoff": "2026-03-11T19:45:00Z",
      "duration": 2
    },
    {
      "league": "English Championship",
      "home": "Middlesbrough",
      "home_logo": "https://i1.wp.com/api.sofascore1.com/api/v1/team/169/image",
      "away": "Charlton Athletic",
      "away_logo": "https://i1.wp.com/api.sofascore1.com/api/v1/team/141/image",
      "kickoff": "2026-03-11T19:45:00Z",
      "duration": 2
    },
    {
      "league": "English Championship",
      "home": "Oxford United",
      "home_logo": "https://i1.wp.com/api.sofascore1.com/api/v1/team/499/image",
      "away": "Blackburn Rovers",
      "away_logo": "https://i1.wp.com/api.sofascore1.com/api/v1/team/113/image",
      "kickoff": "2026-03-11T19:45:00Z",
      "duration": 2
    },
    {
      "league": "English Championship",
      "home": "West Bromwich Albion",
      "home_logo": "https://i1.wp.com/api.sofascore1.com/api/v1/team/1133/image",
      "away": "Southampton",
      "away_logo": "https://i1.wp.com/api.sofascore1.com/api/v1/team/41/image",
      "kickoff": "2026-03-11T19:45:00Z",
      "duration": 2
    },
    {
      "league": "Brazil Serie A",
      "home": "Mirassol",
      "home_logo": "https://i1.wp.com/api.sofascore1.com/api/v1/team/6561/image",
      "away": "Santos",
      "away_logo": "https://i1.wp.com/api.sofascore1.com/api/v1/team/3001/image",
      "kickoff": "2026-03-11T15:00:00Z",
      "duration": 2.2
    }
  ]
}
